ehforwarderbot/__init__.py
ehforwarderbot/__main__.py
ehforwarderbot/__version__.py
ehforwarderbot/channel.py
ehforwarderbot/chat.py
ehforwarderbot/config.py
ehforwarderbot/constants.py
ehforwarderbot/coordinator.py
ehforwarderbot/exceptions.py
ehforwarderbot/message.py
ehforwarderbot/middleware.py
ehforwarderbot/mimetypes
ehforwarderbot/py.typed
ehforwarderbot/status.py
ehforwarderbot/types.py
ehforwarderbot/utils.py
ehforwarderbot/wizard.py
ehforwarderbot/locale/az_AZ/LC_MESSAGES/ehforwarderbot.mo
ehforwarderbot/locale/az_AZ/LC_MESSAGES/ehforwarderbot.po
ehforwarderbot/locale/en_US/LC_MESSAGES/ehforwarderbot.mo
ehforwarderbot/locale/en_US/LC_MESSAGES/ehforwarderbot.po
ehforwarderbot/locale/es_AR/LC_MESSAGES/ehforwarderbot.mo
ehforwarderbot/locale/es_AR/LC_MESSAGES/ehforwarderbot.po
ehforwarderbot/locale/es_VE/LC_MESSAGES/ehforwarderbot.mo
ehforwarderbot/locale/es_VE/LC_MESSAGES/ehforwarderbot.po
ehforwarderbot/locale/id_ID/LC_MESSAGES/ehforwarderbot.mo
ehforwarderbot/locale/id_ID/LC_MESSAGES/ehforwarderbot.po
ehforwarderbot/locale/it_IT/LC_MESSAGES/ehforwarderbot.mo
ehforwarderbot/locale/it_IT/LC_MESSAGES/ehforwarderbot.po
ehforwarderbot/locale/ja_JP/LC_MESSAGES/ehforwarderbot.mo
ehforwarderbot/locale/ja_JP/LC_MESSAGES/ehforwarderbot.po
ehforwarderbot/locale/ms_MY/LC_MESSAGES/ehforwarderbot.mo
ehforwarderbot/locale/ms_MY/LC_MESSAGES/ehforwarderbot.po
ehforwarderbot/locale/ro_RO/LC_MESSAGES/ehforwarderbot.mo
ehforwarderbot/locale/ro_RO/LC_MESSAGES/ehforwarderbot.po
ehforwarderbot/locale/tr_TR/LC_MESSAGES/ehforwarderbot.mo
ehforwarderbot/locale/tr_TR/LC_MESSAGES/ehforwarderbot.po
ehforwarderbot/locale/zh_CN/LC_MESSAGES/ehforwarderbot.mo
ehforwarderbot/locale/zh_CN/LC_MESSAGES/ehforwarderbot.po
ehforwarderbot/locale/zh_TW/LC_MESSAGES/ehforwarderbot.mo
ehforwarderbot/locale/zh_TW/LC_MESSAGES/ehforwarderbot.po
ehforwarderbot-2.1.1.dist-info/AUTHORS
ehforwarderbot-2.1.1.dist-info/LICENSE.md
ehforwarderbot-2.1.1.dist-info/METADATA
ehforwarderbot-2.1.1.dist-info/WHEEL
ehforwarderbot-2.1.1.dist-info/entry_points.txt
ehforwarderbot-2.1.1.dist-info/top_level.txt
ehforwarderbot-2.1.1.dist-info/RECORD
