Metadata-Version: 2.1
Name: ehforwarderbot
Version: 2.1.1
Summary: An extensible message tunneling chat bot framework.
Home-page: https://github.com/ehForwarderBot/ehForwarderBot
Author: Eana Hufwe
Author-email: ilove@1a23.com
License: AGPLv3+
Project-URL: Documentation, https://ehForwarderBot.readthedocs.io
Project-URL: GitHub Discussions, https://github.com/ehForwarderBot/ehForwarderBot/discussions
Project-URL: Telegram Chat, https://t.me/EFBSupport
Keywords: EFB,EH Forwarder Bot,Chat tunneling,IM,messaging
Platform: UNKNOWN
Classifier: Development Status :: 4 - Beta
Classifier: License :: OSI Approved :: GNU Affero General Public License v3 or later (AGPLv3+)
Classifier: Intended Audience :: Developers
Classifier: Intended Audience :: End Users/Desktop
Classifier: Programming Language :: Python :: 3 :: Only
Classifier: Programming Language :: Python :: 3.6
Classifier: Programming Language :: Python :: 3.7
Classifier: Topic :: Communications :: Chat
Classifier: Topic :: Software Development :: Libraries :: Application Frameworks
Classifier: Typing :: Typed
Requires-Python: >=3.6
Requires-Dist: ruamel.yaml
Requires-Dist: bullet
Requires-Dist: cjkwrap
Requires-Dist: typing-extensions
Provides-Extra: telemetry
Requires-Dist: 1a23-telemetry ; extra == 'telemetry'
Provides-Extra: tests
Requires-Dist: pytest ; extra == 'tests'
Requires-Dist: mypy ; extra == 'tests'
Provides-Extra: trace
Requires-Dist: hanging-threads ; extra == 'trace'
